flask_executor/__init__.py
flask_executor/executor.py
flask_executor/futures.py
flask_executor/helpers.py
Flask_Executor-1.0.0.dist-info/LICENSE
Flask_Executor-1.0.0.dist-info/METADATA
Flask_Executor-1.0.0.dist-info/WHEEL
Flask_Executor-1.0.0.dist-info/top_level.txt
Flask_Executor-1.0.0.dist-info/RECORD
