Metadata-Version: 2.1
Name: Flask-Executor
Version: 1.0.0
Summary: An easy to use Flask wrapper for concurrent.futures
Home-page: https://github.com/dchevell/flask-executor
Author: Dave Chevell
Author-email: chevell@gmail.com
License: MIT
Keywords: flask,concurrent.futures
Classifier: Programming Language :: Python :: 3
Classifier: License :: OSI Approved :: MIT License
Classifier: Operating System :: OS Independent
Provides-Extra: test
License-File: LICENSE
